brkraw/__init__.py
brkraw/api/__init__.py
brkraw/api/types.py
brkraw/apps/__init__.py
brkraw/apps/addon/__init__.py
brkraw/apps/addon/core.py
brkraw/apps/addon/dependencies.py
brkraw/apps/addon/installation.py
brkraw/apps/addon/io.py
brkraw/apps/hook/__init__.py
brkraw/apps/hook/core.py
brkraw/apps/loader/__init__.py
brkraw/apps/loader/core.py
brkraw/apps/loader/formatter.py
brkraw/apps/loader/helper.py
brkraw/apps/loader/types.py
brkraw/apps/loader/info/__init__.py
brkraw/apps/loader/info/scan.py
brkraw/apps/loader/info/scan.yaml
brkraw/apps/loader/info/study.py
brkraw/apps/loader/info/study.yaml
brkraw/apps/loader/info/transform.py
brkraw/cli/__init__.py
brkraw/cli/hook_args.py
brkraw/cli/main.py
brkraw/cli/utils.py
brkraw/cli/commands/__init__.py
brkraw/cli/commands/addon.py
brkraw/cli/commands/cache.py
brkraw/cli/commands/config.py
brkraw/cli/commands/convert.py
brkraw/cli/commands/hook.py
brkraw/cli/commands/info.py
brkraw/cli/commands/init.py
brkraw/cli/commands/params.py
brkraw/cli/commands/prune.py
brkraw/cli/commands/session.py
brkraw/core/__init__.py
brkraw/core/cache.py
brkraw/core/config.py
brkraw/core/entrypoints.py
brkraw/core/formatter.py
brkraw/core/fs.py
brkraw/core/jcamp.py
brkraw/core/layout.py
brkraw/core/parameters.py
brkraw/core/zip.py
brkraw/dataclasses/__init__.py
brkraw/dataclasses/node.py
brkraw/dataclasses/reco.py
brkraw/dataclasses/scan.py
brkraw/dataclasses/study.py
brkraw/default/__init__.py
brkraw/default/pruner_specs/deid4share.yaml
brkraw/default/rules/00_default.yaml
brkraw/default/specs/metadata_dicom.yaml
brkraw/default/specs/metadata_transforms.py
brkraw/resolver/__init__.py
brkraw/resolver/affine.py
brkraw/resolver/datatype.py
brkraw/resolver/fid.py
brkraw/resolver/helpers.py
brkraw/resolver/image.py
brkraw/resolver/nifti.py
brkraw/resolver/shape.py
brkraw/schema/__init__.py
brkraw/schema/context_map.yaml
brkraw/schema/meta.yaml
brkraw/schema/niftiheader.yaml
brkraw/schema/pruner.yaml
brkraw/schema/remapper.yaml
brkraw-0.5.6.dist-info/METADATA
brkraw-0.5.6.dist-info/WHEEL
brkraw-0.5.6.dist-info/entry_points.txt
brkraw-0.5.6.dist-info/licenses/LICENSE
brkraw-0.5.6.dist-info/RECORD
